<?xml version="1.0" encoding="utf-8"?>
<!DOCTYPE hibernate-mapping PUBLIC "-//Hibernate/Hibernate Mapping DTD 3.0//EN"
"http://www.hibernate.org/dtd/hibernate-mapping-3.0.dtd">
<!-- 
    Mapping file autogenerated by MyEclipse Persistence Tools
-->
<hibernate-mapping>
    <class name="com.efun.po.TGameCashuMoney" table="t_game_cashU_money" >
        <id name="ugmid" type="java.lang.Long">
            <column name="ugmid" />
            <generator class="assigned" />
        </id>
        <property name="gameCode" type="string">
            <column name="gameCode" length="32"/>
        </property>
        <property name="serverCode" type="string">
            <column name="serverCode" length="32" />
        </property>
        <property name="moneyType" type="string">
            <column name="moneyType" length="20" />
        </property>
        <property name="payFrom" type="string">
            <column name="payFrom" length="30" />
        </property>
        <property name="uid" type="java.lang.Long">
            <column name="uid" />
        </property>
        <property name="gamePay" type="java.lang.Float">
            <column name="gamePay" precision="12" scale="0" />
        </property>
         <property name="twCoin" type="java.lang.Float">
            <column name="twCoin" precision="12" scale="0" />
        </property>
        <property name="usd" type="java.lang.Float">
            <column name="usd" precision="12" scale="0" />
        </property>
         <property name="stone" type="java.lang.Long">
            <column name="stone" precision="12" scale="0" />
        </property> 
        <property name="resultCode" type="string">
            <column name="resultCode" length="20" />
        </property>
        <property name="payStatus" type="string">
            <column name="payStatus" length="16" />
        </property>
        <property name="efunOrderId" type="string">
            <column name="efunOrderId" length="50" />
        </property>
         <property name="creditId" type="string">
            <column name="creditId" length="50" />
        </property>
        <property name="cashUOrderId" type="string">
            <column name="cashUOrderId" length="50" />
        </property>
         <property name="payType" type="string">
            <column name="payType" length="10" />
        </property>
        <property name="createdTime" type="timestamp">
            <column name="createdTime" length="19" />
        </property>
        <property name="modifiedTime" type="timestamp">
            <column name="modifiedTime" length="19" />
        </property>
         <property name="remark" type="string">
            <column name="remark" length="80" />
        </property>
    </class>
</hibernate-mapping>
