<?xml version="1.0" encoding="utf-8"?>
<!DOCTYPE hibernate-mapping PUBLIC "-//Hibernate/Hibernate Mapping DTD 3.0//EN"
"http://www.hibernate.org/dtd/hibernate-mapping-3.0.dtd">
<!-- 
    Mapping file autogenerated by MyEclipse Persistence Tools
-->
<hibernate-mapping>
    <class name="com.efun.po.TManufacturerOrder" table="t_manufacturer_order">
        <id name="id" type="java.lang.Integer">
            <column name="id" />
            <generator class="identity" />
        </id>
        <property name="userid" type="java.lang.Long">
            <column name="userid">
                <comment>用户ID</comment>
            </column>
        </property>
        <property name="gameCode" type="java.lang.String">
            <column name="gameCode" length="20">
                <comment>游戏Code</comment>
            </column>
        </property>
        <property name="serverCode" type="java.lang.String">
            <column name="serverCode" length="32">
                <comment>游戏服Code</comment>
            </column>
        </property>
        <property name="efunOrderId" type="java.lang.String">
            <column name="efunOrderId" length="50">
                <comment>efun订单号</comment>
            </column>
        </property>
        <property name="thirdOrderId" type="java.lang.String">
            <column name="thirdOrderId" length="100" />
        </property>
        <property name="payMoney" type="java.lang.Float">
            <column name="payMoney" precision="12" scale="0">
                <comment>储值金额</comment>
            </column>
        </property>
        <property name="stone" type="java.lang.Float">
            <column name="stone" precision="12" scale="0">
                <comment>获得游戏币</comment>
            </column>
        </property>
        <property name="moneyType" type="java.lang.String">
            <column name="moneyType" length="20">
                <comment>币种类型</comment>
            </column>
        </property>
        <property name="orderTime" type="java.util.Date">
            <column name="orderTime" length="19">
                <comment>币种类型</comment>
            </column>
        </property>
        <property name="flag" type="java.lang.String">
            <column name="flag" length="20">
                <comment>系统类型</comment>
            </column>
        </property>
        <property name="item" type="java.lang.String">
            <column name="item" length="30">
                <comment>预留字段</comment>
            </column>
        </property>
        <property name="deleted" type="java.lang.String">
            <column name="deleted" length="2" />
        </property>
    </class>
</hibernate-mapping>
